LICENSE
README.md
setup.py
src/pwmanager/__init__.py
src/pwmanager/accounts.py
src/pwmanager/config.py
src/pwmanager/debug.py
src/pwmanager/gitwrap.py
src/pwmanager/globallock.py
src/pwmanager/gpgwrap.py
src/pwmanager/ldapwrap.py
src/pwmanager/pwmanager.py
src/pwmanager.egg-info/PKG-INFO
src/pwmanager.egg-info/SOURCES.txt
src/pwmanager.egg-info/dependency_links.txt
src/pwmanager.egg-info/entry_points.txt
src/pwmanager.egg-info/requires.txt
src/pwmanager.egg-info/top_level.txt
src/pwmanager/data/pwmanager.conf.sample