Metadata-Version: 2.1
Name: pwmanager
Version: 1.6
Summary: Manage passwords in a git backed encrypted gnupg database with LDAP support
Home-page: https://github.com/andbof/pwmanager
Author: Andreas Bofjäll
Author-email: andreas@gazonk.org
License: MIT
Keywords: password manager gpg gnupg ldap
Platform: UNKNOWN
Classifier: Development Status :: 4 - Beta
Classifier: Environment :: Console
Classifier: Topic :: Utilities
Classifier: License :: OSI Approved :: MIT License
License-File: LICENSE
